digimon/__init__.py
digimon/client.py
pydigimon-0.0.5.dist-info/LICENSE
pydigimon-0.0.5.dist-info/METADATA
pydigimon-0.0.5.dist-info/WHEEL
pydigimon-0.0.5.dist-info/top_level.txt
pydigimon-0.0.5.dist-info/RECORD
