Metadata-Version: 2.1
Name: pydigimon
Version: 0.0.5
Summary: Client to get Digimon
Home-page: https://github.com/gdvalderrama/pydigimon
Author: Guiomar Valderrama
License: UNKNOWN
Project-URL: Bug Tracker, https://github.com/gdvalderrama/pydigimon/issues
Platform: UNKNOWN
Classifier: Programming Language :: Python :: 3
Classifier: License :: OSI Approved :: MIT License
Classifier: Operating System :: OS Independent
Requires-Python: >=3.6
License-File: LICENSE
Requires-Dist: requests
